{
  "asOf": "2026-07-06 00:05 UTC",
  "series": {
    "us10y": {
      "label": "US 10-Year Treasury Yield",
      "unit": "%",
      "current": 4.49,
      "chg30d": 0.67,
      "chg90d": 3.99,
      "level1yPct": 75.2
    },
    "us3m": {
      "label": "US 3-Month Yield",
      "unit": "%",
      "current": 3.67,
      "chg30d": 1.38,
      "chg90d": 1.69,
      "level1yPct": 21.9
    },
    "crude": {
      "label": "Crude Oil (WTI)",
      "unit": "$/bbl",
      "current": 68.24,
      "chg30d": -24.63,
      "chg90d": -39.29,
      "level1yPct": 22.5
    },
    "usdinr": {
      "label": "USD/INR",
      "unit": "\u20b9",
      "current": 95.2,
      "chg30d": -0.62,
      "chg90d": 2.57,
      "level1yPct": 87.7
    },
    "dxy": {
      "label": "US Dollar Index",
      "unit": "",
      "current": 100.88,
      "chg30d": 0.81,
      "chg90d": 0.9,
      "level1yPct": 86.5
    },
    "vix": {
      "label": "VIX (Volatility Index)",
      "unit": "",
      "current": 16.15,
      "chg30d": 2.41,
      "chg90d": -32.34,
      "level1yPct": 15.2
    },
    "gold": {
      "label": "Gold",
      "unit": "$/oz",
      "current": 4194.9,
      "chg30d": -3.28,
      "chg90d": -9.92,
      "level1yPct": 44.5
    },
    "copper": {
      "label": "Copper",
      "unit": "$/lb",
      "current": 6.23,
      "chg30d": -0.47,
      "chg90d": 11.65,
      "level1yPct": 81.9
    },
    "in10y": {
      "label": "India 10-Year G-Sec (manual constant, updated 2026-07)",
      "unit": "%",
      "current": 6.8,
      "chg30d": null,
      "chg90d": null,
      "level1yPct": null,
      "source": "manual \u2014 RBI/CCIL published yield; update the constant in fetch_macro.py when it moves materially"
    }
  }
}